linformer/__init__.py
linformer/linformer.py
linformer/reversible.py
linformer-0.2.3.dist-info/LICENSE
linformer-0.2.3.dist-info/METADATA
linformer-0.2.3.dist-info/WHEEL
linformer-0.2.3.dist-info/top_level.txt
linformer-0.2.3.dist-info/RECORD
